torancell/__init__.py
torancell-0.10.1.dist-info/METADATA
torancell-0.10.1.dist-info/WHEEL
torancell-0.10.1.dist-info/top_level.txt
torancell-0.10.1.dist-info/RECORD
