Metadata-Version: 2.1
Name: torancell
Version: 0.10.1
Summary: I like metapod, You like metapod.
Home-page: UNKNOWN
Author: PyPI Sanagi
Author-email: sanagipypi0011@gmail.com
License: UNKNOWN
Platform: UNKNOWN
Requires-Dist: mahjong
Requires-Dist: requests
